tedtest/__init__.py
tedtest/Diagram/__init__.py
tedtest/Diagram/graph.py
tedtest/Diagram/objects.py
tedtest/Exceptions/__init__.py
tedtest/Exceptions/base.py
tedtest/UnitTest/Objects.py
tedtest/UnitTest/Results.py
tedtest/UnitTest/TEDTest.py
tedtest/UnitTest/TestSuite.py
tedtest/UnitTest/Testing.py
tedtest/UnitTest/__init__.py
tedtest/UnitTest/Asserts/AssertThat.py
tedtest/UnitTest/Asserts/Asserts.py
tedtest/UnitTest/Asserts/__init__.py
tedtest-1.0.1.dist-info/METADATA
tedtest-1.0.1.dist-info/WHEEL
tedtest-1.0.1.dist-info/entry_points.txt
tedtest-1.0.1.dist-info/licenses/LICENSE
tedtest-1.0.1.dist-info/RECORD
