Metadata-Version: 2.1
Name: tedtest
Version: 1.0.1
Summary: Simple python testing framework
Project-URL: Homepage, https://github.com/Tired-Fox/TEDTest
Project-URL: Documentation, https://tired-fox.github.io/TEDTest/
Author-email: Tired Fox <zboehm104@gmail.com>
License-File: LICENSE
Classifier: License :: OSI Approved :: MIT License
Classifier: Operating System :: OS Independent
Classifier: Programming Language :: Python :: 3
Requires-Python: >=3.7
Requires-Dist: teddecor>=1.0.2
